financecalculator.py
mindpowered_financecalculator/FinanceCalculator.py
mindpowered_financecalculator/__init__.py
mindpowered_financecalculator-0.0.2.dist-info/LICENSE.txt
mindpowered_financecalculator-0.0.2.dist-info/METADATA
mindpowered_financecalculator-0.0.2.dist-info/WHEEL
mindpowered_financecalculator-0.0.2.dist-info/top_level.txt
mindpowered_financecalculator-0.0.2.dist-info/RECORD
