Metadata-Version: 2.1
Name: mindpowered-financecalculator
Version: 0.0.2
Summary: Financial calculations such as Net Present Value, Present Value, Future Value
Home-page: https://mindpowered.dev/
Author: Mind Powered Corporation
Author-email: support@mindpowered.dev
License: MIT
Platform: UNKNOWN
Classifier: Programming Language :: Python :: 3
Classifier: Operating System :: OS Independent
Classifier: License :: OSI Approved :: MIT License
Requires-Dist: mindpowered-maglev
